zipo/__init__.py
zipo-0.0.4.dist-info/LICENSE
zipo-0.0.4.dist-info/METADATA
zipo-0.0.4.dist-info/WHEEL
zipo-0.0.4.dist-info/top_level.txt
zipo-0.0.4.dist-info/RECORD
