Metadata-Version: 2.1
Name: zipo
Version: 0.0.4
Summary: functions.
Home-page: https://github.com/seoul2k/zipp
Author: xiongtianshuo
Author-email: Mr_Xiongts@163.com
Maintainer: xiongtianshuo
Maintainer-email: seoul1k@163.com
License: BSD License
Project-URL: Bug Tracker, https://github.com/seoul2k/zipp/issues
Platform: all
Classifier: Development Status :: 4 - Beta
Classifier: Operating System :: OS Independent
Classifier: Intended Audience :: Developers
Classifier: License :: OSI Approved :: BSD License
Classifier: Programming Language :: Python
Classifier: Programming Language :: Python :: Implementation
Classifier: Programming Language :: Python :: 3
Classifier: Programming Language :: Python :: 3.1
Classifier: Programming Language :: Python :: 3.2
Classifier: Programming Language :: Python :: 3.5
Classifier: Programming Language :: Python :: 3.6
Classifier: Programming Language :: Python :: 3.8
Classifier: Topic :: Software Development :: Libraries
License-File: LICENSE
